query_diet/__init__.py
query_diet/analyzer.py
query_diet/comment.py
query_diet/context.py
query_diet/core.py
query_diet/defaults.py
query_diet/middleware.py
query_diet/monkey.py
query_diet/scoped.py
query_diet/utils.py
query_diet-0.1.1.dist-info/LICENSE
query_diet-0.1.1.dist-info/WHEEL
query_diet-0.1.1.dist-info/METADATA
query_diet-0.1.1.dist-info/RECORD
