Metadata-Version: 2.1
Name: query-diet
Version: 0.1.1
Summary: A diet for losing query fats.
Home-page: https://github.com/mselee/query_diet
Author: Mohamed Seleem
Author-email: hi@mselee.com
Requires-Python: >=3.8,<4.0
Classifier: Programming Language :: Python :: 3
Classifier: Programming Language :: Python :: 3.8
Requires-Dist: pandas (>=1.0.1,<2.0.0)
Requires-Dist: shortuuid (>=0.5.0,<0.6.0)
